jenkins_validate/__init__.py
jenkins_validate/auto_validator.py
jenkins_validate-0.0.12.dist-info/LICENSE
jenkins_validate-0.0.12.dist-info/METADATA
jenkins_validate-0.0.12.dist-info/WHEEL
jenkins_validate-0.0.12.dist-info/top_level.txt
jenkins_validate-0.0.12.dist-info/RECORD
