Metadata-Version: 2.1
Name: jenkins-validate
Version: 0.0.12
Summary: An auto validate package about jenkins
Home-page: https://github.corp.ebay.com/UFES-dev/ufes-tess-validator
Author: emmawang
Author-email: xuenwang@ebay.com
License: UNKNOWN
Platform: UNKNOWN
Classifier: Programming Language :: Python :: 3
Classifier: License :: OSI Approved :: MIT License
Classifier: Operating System :: OS Independent
Requires-Python: >=3.6
